jjz/__init__.py
jjz/cli.py
jjz-0.0.1.dist-info/METADATA
jjz-0.0.1.dist-info/WHEEL
jjz-0.0.1.dist-info/entry_points.txt
jjz-0.0.1.dist-info/top_level.txt
jjz-0.0.1.dist-info/RECORD
