Metadata-Version: 2.4
Name: jjz
Version: 0.0.1
Summary: Powerful CLI tool with multiple aliases (jujutsu/jutsu/jjz/jj2) - Lightning Fast Commands
Author-email: dai-motoki <kanri@kandaquantum.co.jp>
Project-URL: Homepage, https://github.com/dai-motoki/jujutsu
Project-URL: Repository, https://github.com/dai-motoki/jujutsu
Classifier: Development Status :: 3 - Alpha
Classifier: Environment :: Console
Classifier: Intended Audience :: Developers
Classifier: Operating System :: OS Independent
Classifier: Programming Language :: Python :: 3
Classifier: Programming Language :: Python :: 3.9
Classifier: Programming Language :: Python :: 3.10
Classifier: Programming Language :: Python :: 3.11
Classifier: Programming Language :: Python :: 3.12
Classifier: Topic :: Software Development :: Libraries :: Python Modules
Requires-Python: >=3.9
